wplinks
