Metadata-Version: 1.0
Name: wplinks
Version: 0.0.2
Summary: find wikipedia articles that links to a website
Home-page: http://github.com/edsu/wplinks
Author: Ed Summers
Author-email: ehs@pobox.com
License: http://creativecommons.org/publicdomain/zero/1.0/
Platform: UNKNOWN
